{
  "hizb_number": 51,
  "recitation_id": 2,
  "reciter_name": "AbdulBaset AbdulSamad",
  "style": "Murattal",
  "total_verses": 90,
  "verses": [
    {
      "verse_key": "46:1",
      "audio_path": "/reciters/2/verses/ayah/46_1.mp3"
    },
    {
      "verse_key": "46:2",
      "audio_path": "/reciters/2/verses/ayah/46_2.mp3"
    },
    {
      "verse_key": "46:3",
      "audio_path": "/reciters/2/verses/ayah/46_3.mp3"
    },
    {
      "verse_key": "46:4",
      "audio_path": "/reciters/2/verses/ayah/46_4.mp3"
    },
    {
      "verse_key": "46:5",
      "audio_path": "/reciters/2/verses/ayah/46_5.mp3"
    },
    {
      "verse_key": "46:6",
      "audio_path": "/reciters/2/verses/ayah/46_6.mp3"
    },
    {
      "verse_key": "46:7",
      "audio_path": "/reciters/2/verses/ayah/46_7.mp3"
    },
    {
      "verse_key": "46:8",
      "audio_path": "/reciters/2/verses/ayah/46_8.mp3"
    },
    {
      "verse_key": "46:9",
      "audio_path": "/reciters/2/verses/ayah/46_9.mp3"
    },
    {
      "verse_key": "46:10",
      "audio_path": "/reciters/2/verses/ayah/46_10.mp3"
    },
    {
      "verse_key": "46:11",
      "audio_path": "/reciters/2/verses/ayah/46_11.mp3"
    },
    {
      "verse_key": "46:12",
      "audio_path": "/reciters/2/verses/ayah/46_12.mp3"
    },
    {
      "verse_key": "46:13",
      "audio_path": "/reciters/2/verses/ayah/46_13.mp3"
    },
    {
      "verse_key": "46:14",
      "audio_path": "/reciters/2/verses/ayah/46_14.mp3"
    },
    {
      "verse_key": "46:15",
      "audio_path": "/reciters/2/verses/ayah/46_15.mp3"
    },
    {
      "verse_key": "46:16",
      "audio_path": "/reciters/2/verses/ayah/46_16.mp3"
    },
    {
      "verse_key": "46:17",
      "audio_path": "/reciters/2/verses/ayah/46_17.mp3"
    },
    {
      "verse_key": "46:18",
      "audio_path": "/reciters/2/verses/ayah/46_18.mp3"
    },
    {
      "verse_key": "46:19",
      "audio_path": "/reciters/2/verses/ayah/46_19.mp3"
    },
    {
      "verse_key": "46:20",
      "audio_path": "/reciters/2/verses/ayah/46_20.mp3"
    },
    {
      "verse_key": "46:21",
      "audio_path": "/reciters/2/verses/ayah/46_21.mp3"
    },
    {
      "verse_key": "46:22",
      "audio_path": "/reciters/2/verses/ayah/46_22.mp3"
    },
    {
      "verse_key": "46:23",
      "audio_path": "/reciters/2/verses/ayah/46_23.mp3"
    },
    {
      "verse_key": "46:24",
      "audio_path": "/reciters/2/verses/ayah/46_24.mp3"
    },
    {
      "verse_key": "46:25",
      "audio_path": "/reciters/2/verses/ayah/46_25.mp3"
    },
    {
      "verse_key": "46:26",
      "audio_path": "/reciters/2/verses/ayah/46_26.mp3"
    },
    {
      "verse_key": "46:27",
      "audio_path": "/reciters/2/verses/ayah/46_27.mp3"
    },
    {
      "verse_key": "46:28",
      "audio_path": "/reciters/2/verses/ayah/46_28.mp3"
    },
    {
      "verse_key": "46:29",
      "audio_path": "/reciters/2/verses/ayah/46_29.mp3"
    },
    {
      "verse_key": "46:30",
      "audio_path": "/reciters/2/verses/ayah/46_30.mp3"
    },
    {
      "verse_key": "46:31",
      "audio_path": "/reciters/2/verses/ayah/46_31.mp3"
    },
    {
      "verse_key": "46:32",
      "audio_path": "/reciters/2/verses/ayah/46_32.mp3"
    },
    {
      "verse_key": "46:33",
      "audio_path": "/reciters/2/verses/ayah/46_33.mp3"
    },
    {
      "verse_key": "46:34",
      "audio_path": "/reciters/2/verses/ayah/46_34.mp3"
    },
    {
      "verse_key": "46:35",
      "audio_path": "/reciters/2/verses/ayah/46_35.mp3"
    },
    {
      "verse_key": "47:1",
      "audio_path": "/reciters/2/verses/ayah/47_1.mp3"
    },
    {
      "verse_key": "47:2",
      "audio_path": "/reciters/2/verses/ayah/47_2.mp3"
    },
    {
      "verse_key": "47:3",
      "audio_path": "/reciters/2/verses/ayah/47_3.mp3"
    },
    {
      "verse_key": "47:4",
      "audio_path": "/reciters/2/verses/ayah/47_4.mp3"
    },
    {
      "verse_key": "47:5",
      "audio_path": "/reciters/2/verses/ayah/47_5.mp3"
    },
    {
      "verse_key": "47:6",
      "audio_path": "/reciters/2/verses/ayah/47_6.mp3"
    },
    {
      "verse_key": "47:7",
      "audio_path": "/reciters/2/verses/ayah/47_7.mp3"
    },
    {
      "verse_key": "47:8",
      "audio_path": "/reciters/2/verses/ayah/47_8.mp3"
    },
    {
      "verse_key": "47:9",
      "audio_path": "/reciters/2/verses/ayah/47_9.mp3"
    },
    {
      "verse_key": "47:10",
      "audio_path": "/reciters/2/verses/ayah/47_10.mp3"
    },
    {
      "verse_key": "47:11",
      "audio_path": "/reciters/2/verses/ayah/47_11.mp3"
    },
    {
      "verse_key": "47:12",
      "audio_path": "/reciters/2/verses/ayah/47_12.mp3"
    },
    {
      "verse_key": "47:13",
      "audio_path": "/reciters/2/verses/ayah/47_13.mp3"
    },
    {
      "verse_key": "47:14",
      "audio_path": "/reciters/2/verses/ayah/47_14.mp3"
    },
    {
      "verse_key": "47:15",
      "audio_path": "/reciters/2/verses/ayah/47_15.mp3"
    },
    {
      "verse_key": "47:16",
      "audio_path": "/reciters/2/verses/ayah/47_16.mp3"
    },
    {
      "verse_key": "47:17",
      "audio_path": "/reciters/2/verses/ayah/47_17.mp3"
    },
    {
      "verse_key": "47:18",
      "audio_path": "/reciters/2/verses/ayah/47_18.mp3"
    },
    {
      "verse_key": "47:19",
      "audio_path": "/reciters/2/verses/ayah/47_19.mp3"
    },
    {
      "verse_key": "47:20",
      "audio_path": "/reciters/2/verses/ayah/47_20.mp3"
    },
    {
      "verse_key": "47:21",
      "audio_path": "/reciters/2/verses/ayah/47_21.mp3"
    },
    {
      "verse_key": "47:22",
      "audio_path": "/reciters/2/verses/ayah/47_22.mp3"
    },
    {
      "verse_key": "47:23",
      "audio_path": "/reciters/2/verses/ayah/47_23.mp3"
    },
    {
      "verse_key": "47:24",
      "audio_path": "/reciters/2/verses/ayah/47_24.mp3"
    },
    {
      "verse_key": "47:25",
      "audio_path": "/reciters/2/verses/ayah/47_25.mp3"
    },
    {
      "verse_key": "47:26",
      "audio_path": "/reciters/2/verses/ayah/47_26.mp3"
    },
    {
      "verse_key": "47:27",
      "audio_path": "/reciters/2/verses/ayah/47_27.mp3"
    },
    {
      "verse_key": "47:28",
      "audio_path": "/reciters/2/verses/ayah/47_28.mp3"
    },
    {
      "verse_key": "47:29",
      "audio_path": "/reciters/2/verses/ayah/47_29.mp3"
    },
    {
      "verse_key": "47:30",
      "audio_path": "/reciters/2/verses/ayah/47_30.mp3"
    },
    {
      "verse_key": "47:31",
      "audio_path": "/reciters/2/verses/ayah/47_31.mp3"
    },
    {
      "verse_key": "47:32",
      "audio_path": "/reciters/2/verses/ayah/47_32.mp3"
    },
    {
      "verse_key": "47:33",
      "audio_path": "/reciters/2/verses/ayah/47_33.mp3"
    },
    {
      "verse_key": "47:34",
      "audio_path": "/reciters/2/verses/ayah/47_34.mp3"
    },
    {
      "verse_key": "47:35",
      "audio_path": "/reciters/2/verses/ayah/47_35.mp3"
    },
    {
      "verse_key": "47:36",
      "audio_path": "/reciters/2/verses/ayah/47_36.mp3"
    },
    {
      "verse_key": "47:37",
      "audio_path": "/reciters/2/verses/ayah/47_37.mp3"
    },
    {
      "verse_key": "47:38",
      "audio_path": "/reciters/2/verses/ayah/47_38.mp3"
    },
    {
      "verse_key": "48:1",
      "audio_path": "/reciters/2/verses/ayah/48_1.mp3"
    },
    {
      "verse_key": "48:2",
      "audio_path": "/reciters/2/verses/ayah/48_2.mp3"
    },
    {
      "verse_key": "48:3",
      "audio_path": "/reciters/2/verses/ayah/48_3.mp3"
    },
    {
      "verse_key": "48:4",
      "audio_path": "/reciters/2/verses/ayah/48_4.mp3"
    },
    {
      "verse_key": "48:5",
      "audio_path": "/reciters/2/verses/ayah/48_5.mp3"
    },
    {
      "verse_key": "48:6",
      "audio_path": "/reciters/2/verses/ayah/48_6.mp3"
    },
    {
      "verse_key": "48:7",
      "audio_path": "/reciters/2/verses/ayah/48_7.mp3"
    },
    {
      "verse_key": "48:8",
      "audio_path": "/reciters/2/verses/ayah/48_8.mp3"
    },
    {
      "verse_key": "48:9",
      "audio_path": "/reciters/2/verses/ayah/48_9.mp3"
    },
    {
      "verse_key": "48:10",
      "audio_path": "/reciters/2/verses/ayah/48_10.mp3"
    },
    {
      "verse_key": "48:11",
      "audio_path": "/reciters/2/verses/ayah/48_11.mp3"
    },
    {
      "verse_key": "48:12",
      "audio_path": "/reciters/2/verses/ayah/48_12.mp3"
    },
    {
      "verse_key": "48:13",
      "audio_path": "/reciters/2/verses/ayah/48_13.mp3"
    },
    {
      "verse_key": "48:14",
      "audio_path": "/reciters/2/verses/ayah/48_14.mp3"
    },
    {
      "verse_key": "48:15",
      "audio_path": "/reciters/2/verses/ayah/48_15.mp3"
    },
    {
      "verse_key": "48:16",
      "audio_path": "/reciters/2/verses/ayah/48_16.mp3"
    },
    {
      "verse_key": "48:17",
      "audio_path": "/reciters/2/verses/ayah/48_17.mp3"
    }
  ]
}