{
  "page_number": 136,
  "recitation_id": 2,
  "reciter_name": "AbdulBaset AbdulSamad",
  "style": "Murattal",
  "total_verses": 5,
  "verses": [
    {
      "verse_key": "6:69",
      "audio_path": "/reciters/2/verses/ayah/6_69.mp3"
    },
    {
      "verse_key": "6:70",
      "audio_path": "/reciters/2/verses/ayah/6_70.mp3"
    },
    {
      "verse_key": "6:71",
      "audio_path": "/reciters/2/verses/ayah/6_71.mp3"
    },
    {
      "verse_key": "6:72",
      "audio_path": "/reciters/2/verses/ayah/6_72.mp3"
    },
    {
      "verse_key": "6:73",
      "audio_path": "/reciters/2/verses/ayah/6_73.mp3"
    }
  ]
}