{
  "page_number": 517,
  "recitation_id": 2,
  "reciter_name": "AbdulBaset AbdulSamad",
  "style": "Murattal",
  "total_verses": 7,
  "verses": [
    {
      "verse_key": "49:12",
      "audio_path": "/reciters/2/verses/ayah/49_12.mp3"
    },
    {
      "verse_key": "49:13",
      "audio_path": "/reciters/2/verses/ayah/49_13.mp3"
    },
    {
      "verse_key": "49:14",
      "audio_path": "/reciters/2/verses/ayah/49_14.mp3"
    },
    {
      "verse_key": "49:15",
      "audio_path": "/reciters/2/verses/ayah/49_15.mp3"
    },
    {
      "verse_key": "49:16",
      "audio_path": "/reciters/2/verses/ayah/49_16.mp3"
    },
    {
      "verse_key": "49:17",
      "audio_path": "/reciters/2/verses/ayah/49_17.mp3"
    },
    {
      "verse_key": "49:18",
      "audio_path": "/reciters/2/verses/ayah/49_18.mp3"
    }
  ]
}