{
  "page_number": 528,
  "recitation_id": 2,
  "reciter_name": "AbdulBaset AbdulSamad",
  "style": "Murattal",
  "total_verses": 24,
  "verses": [
    {
      "verse_key": "53:45",
      "audio_path": "/reciters/2/verses/ayah/53_45.mp3"
    },
    {
      "verse_key": "53:46",
      "audio_path": "/reciters/2/verses/ayah/53_46.mp3"
    },
    {
      "verse_key": "53:47",
      "audio_path": "/reciters/2/verses/ayah/53_47.mp3"
    },
    {
      "verse_key": "53:48",
      "audio_path": "/reciters/2/verses/ayah/53_48.mp3"
    },
    {
      "verse_key": "53:49",
      "audio_path": "/reciters/2/verses/ayah/53_49.mp3"
    },
    {
      "verse_key": "53:50",
      "audio_path": "/reciters/2/verses/ayah/53_50.mp3"
    },
    {
      "verse_key": "53:51",
      "audio_path": "/reciters/2/verses/ayah/53_51.mp3"
    },
    {
      "verse_key": "53:52",
      "audio_path": "/reciters/2/verses/ayah/53_52.mp3"
    },
    {
      "verse_key": "53:53",
      "audio_path": "/reciters/2/verses/ayah/53_53.mp3"
    },
    {
      "verse_key": "53:54",
      "audio_path": "/reciters/2/verses/ayah/53_54.mp3"
    },
    {
      "verse_key": "53:55",
      "audio_path": "/reciters/2/verses/ayah/53_55.mp3"
    },
    {
      "verse_key": "53:56",
      "audio_path": "/reciters/2/verses/ayah/53_56.mp3"
    },
    {
      "verse_key": "53:57",
      "audio_path": "/reciters/2/verses/ayah/53_57.mp3"
    },
    {
      "verse_key": "53:58",
      "audio_path": "/reciters/2/verses/ayah/53_58.mp3"
    },
    {
      "verse_key": "53:59",
      "audio_path": "/reciters/2/verses/ayah/53_59.mp3"
    },
    {
      "verse_key": "53:60",
      "audio_path": "/reciters/2/verses/ayah/53_60.mp3"
    },
    {
      "verse_key": "53:61",
      "audio_path": "/reciters/2/verses/ayah/53_61.mp3"
    },
    {
      "verse_key": "53:62",
      "audio_path": "/reciters/2/verses/ayah/53_62.mp3"
    },
    {
      "verse_key": "54:1",
      "audio_path": "/reciters/2/verses/ayah/54_1.mp3"
    },
    {
      "verse_key": "54:2",
      "audio_path": "/reciters/2/verses/ayah/54_2.mp3"
    },
    {
      "verse_key": "54:3",
      "audio_path": "/reciters/2/verses/ayah/54_3.mp3"
    },
    {
      "verse_key": "54:4",
      "audio_path": "/reciters/2/verses/ayah/54_4.mp3"
    },
    {
      "verse_key": "54:5",
      "audio_path": "/reciters/2/verses/ayah/54_5.mp3"
    },
    {
      "verse_key": "54:6",
      "audio_path": "/reciters/2/verses/ayah/54_6.mp3"
    }
  ]
}